ansi_escape_code/__init__.py
ansi_escape_code/progressbar.py
circuitpython_ansi_escape_code-1.3.0.dist-info/licenses/LICENSE
circuitpython_ansi_escape_code-1.3.0.dist-info/METADATA
circuitpython_ansi_escape_code-1.3.0.dist-info/WHEEL
circuitpython_ansi_escape_code-1.3.0.dist-info/top_level.txt
circuitpython_ansi_escape_code-1.3.0.dist-info/RECORD
