Metadata-Version: 2.4
Name: circuitpython-ansi-escape-code
Version: 1.3.0
Summary: simple helper library for common ANSI escape codes
Home-page: https://github.com/s-light/CircuitPython_ansi_escape_code.git
Author: Stefan Krüger
Author-email: Stefan Krüger <git@s-light.eu>
License: MIT
Project-URL: Homepage, https://github.com/s-light/CircuitPython_ansi_escape_code
Keywords: adafruit,blinka,circuitpython,micropython,ansi_escape_code,terminal,,ANSI,,color,,position
Classifier: Intended Audience :: Developers
Classifier: Topic :: Software Development :: Libraries
Classifier: Topic :: Software Development :: Embedded Systems
Classifier: Topic :: System :: Hardware
Classifier: License :: OSI Approved :: MIT License
Classifier: Programming Language :: Python :: 3
License-File: LICENSE
Requires-Dist: Adafruit-Blinka
Provides-Extra: optional
Dynamic: author
Dynamic: home-page
Dynamic: license-file
